{
    "patches": [
        {
            "label": "2026-04-18_00-35-23",
            "content": "@@ -118,16 +118,18 @@\n mt.Print\n+ln\n (a)%0A    \n",
            "lines": "9"
        },
        {
            "label": "2026-04-18_00-35-37",
            "content": "@@ -120,18 +120,16 @@\n .Print(a\n-, \n )%0A    %7D%0A\n",
            "lines": "9"
        },
        {
            "label": "2026-04-18_00-41-06",
            "content": "@@ -120,17 +120,16 @@\n .Print(a\n- \n , )%0A    \n",
            "lines": "9"
        },
        {
            "label": "2026-04-18_00-41-12",
            "content": "@@ -119,18 +119,18 @@\n t.Print(\n- \n a\n+ \n , )%0A    \n",
            "lines": "9"
        },
        {
            "label": "2026-04-18_00-41-22",
            "content": "@@ -84,19 +84,13 @@\n or a\n-, valor\n  := \n+a\n ; a \n@@ -112,28 +112,8 @@\n     \n-if a != 0 %7B%0A       %7D\n  fmt\n@@ -119,17 +119,20 @@\n t.Print(\n-a\n+ a, \n )%0A    %7D%0A\n",
            "lines": "9"
        },
        {
            "label": "2026-04-22_12-57-24",
            "content": "@@ -82,13 +82,8 @@\n  for\n- a ==\n  a, \n@@ -90,18 +90,16 @@\n valor :=\n- a\n  ; a %3C= \n@@ -99,17 +99,16 @@\n ; a %3C= b\n- \n ; a++ %7B%0A\n",
            "lines": "10"
        },
        {
            "label": "2026-04-22_13-01-48",
            "content": "@@ -142,17 +142,16 @@\n        %7D\n-;\n  fmt.Pri\n",
            "lines": "10"
        },
        {
            "label": "2026-04-22_13-02-08",
            "content": "@@ -142,16 +142,17 @@\n        %7D\n+;\n  fmt.Pri\n",
            "lines": "10"
        },
        {
            "label": "2026-04-22_13-16-01",
            "content": "@@ -83,26 +83,42 @@\n for \n-i\n+a == a, valor\n  := a\n+ \n ; \n-i\n+a\n  %3C\n+=\n  b\n+ \n ; \n-i\n+a\n ++\n+ \n %7B%0A  \n@@ -122,16 +122,36 @@\n %0A       \n+if a != 0 %7B%0A       %7D\n  fmt.Pri\n@@ -157,21 +157,15 @@\n int(\n-i\n+a\n )%0A    %7D\n- %0A    \n+%0A\n %7D%0A\n-%0A\n",
            "lines": "10"
        },
        {
            "label": "2026-04-22_13-19-57",
            "content": "@@ -121,15 +121,8 @@\n int(\n-%22%25d %22, \n i)%0A \n",
            "lines": "10"
        },
        {
            "label": "2026-04-22_13-20-19",
            "content": "@@ -116,17 +116,16 @@\n mt.Print\n-f\n (%22%25d %22, \n",
            "lines": "10"
        },
        {
            "label": "2026-04-22_13-20-53",
            "content": "@@ -75,27 +75,8 @@\n &b)%0A\n-    fmt.Print(%22%5B%22)%0A\n     \n",
            "lines": "10"
        },
        {
            "label": "2026-04-22_13-21-45",
            "content": "@@ -158,27 +158,8 @@\n  %7D %0A\n-    fmt.Print(%22%5D%22)%0A\n     \n",
            "lines": "11"
        },
        {
            "label": "2026-04-22_13-22-05",
            "content": "@@ -87,17 +87,16 @@\n Print(%22%5B\n- \n %22)%0A    f\n",
            "lines": "12"
        },
        {
            "label": "2026-04-22_13-22-12",
            "content": "@@ -172,10 +172,8 @@\n rint\n-ln\n (%22%5D%22\n",
            "lines": "12"
        },
        {
            "label": "2026-04-22_13-22-25",
            "content": "package main\nimport \"fmt\"\nfunc main() {\n    var a, b int\n    fmt.Scan(&a, &b)\n    fmt.Print(\"[ \")\n    for i := a; i < b; i++{\n        fmt.Printf(\"%d \", i)\n    } \n    fmt.Println(\"]\")\n    }\n\n",
            "lines": "12"
        }
    ]
}